{"type": "Feature", "id": 12517489, "properties": {"woe:id": 12517489, "woe:parent_id": 1591512, "woe:name": "Ulundi Airport", "woe:placetype": 14, "woe:placetype_name": "Airport", "woe:lang": "ENG", "iso:country": "ZA", "meta:provider": ["geoplanet:7.3.1", "geoplanet:7.3.2", "geoplanet:7.4.0", "geoplanet:7.4.1", "geoplanet:7.5.1", "geoplanet:7.5.2", "geoplanet:7.6.0", "geoplanet:7.8.1", "geoplanet:7.9.0", "geoplanet:7.10.0", "geoplanet:8.0.0", "woeplanet:8.0.0"], "meta:indexed": "2020-08-20T21:02:22.351395", "woe:alias_ENG_V": ["ULD Airport", "ULD"], "meta:updated": "2020-08-22T02:49:23.016763", "woe:hierarchy": {"continent": 24865670, "country": 23424942, "town": 0, "planet": 1, "county": 56189413, "suburb": 0, "state": 2346982, "region": 0, "localadmin": 56189496}, "woe:timezone_id": 28350704, "woe:hash": "kdyqfv5bme3d", "woe:centroid": [31.4153, -28.3172], "geom:latitude": -28.3172, "geom:longitude": 31.4153, "geom:hash": "kdyqfv5bme3d", "woe:latitude": -28.3172, "geom:centroid": [31.4153, -28.3172], "woe:longitude": 31.4153, "woe:repo": "woeplanet-airport-za"}, "geometry": {"coordinates": [31.4153, -28.3172], "type": "Point"}}