{"type": "Feature", "id": 12517412, "geometry": {"type": "Point", "coordinates": [28.13872, -25.98889]}, "properties": {"woe:id": 12517412, "woe:parent_id": 55878060, "woe:name": "Grand Central Airport", "woe:placetype": 14, "woe:placetype_name": "Airport", "woe:lang": "ENG", "iso:country": "ZA", "meta:provider": ["geoplanet:7.3.1", "geoplanet:7.3.2", "geoplanet:7.4.0", "geoplanet:7.4.1", "geoplanet:7.5.1", "geoplanet:7.5.2", "geoplanet:7.6.0", "geoplanet:7.8.1", "geoplanet:7.9.0", "geoplanet:7.10.0", "geoplanet:8.0.0", "woeplanet:8.0.0"], "meta:indexed": "2020-08-20T21:02:22.374738", "woe:alias_FIN_V": ["Grand Centralin Lentokentta"], "woe:alias_DAN_Q": ["Grand Central Lufthavn"], "woe:alias_ENG_V": ["GCJ Airport", "GCJ"], "woe:alias_FRE_Q": ["A\u00e9roport Grand Central"], "woe:alias_FIN_Q": ["Grand Centralin Lentokentt\u00e4"], "woe:alias_SWE_Q": ["Grand Central Flygplats"], "woe:alias_DUT_Q": ["Luchthaven Grand Central"], "meta:updated": "2020-10-14T12:10:56.786411", "woe:alias_ITA_Q": ["Aeroporto Grand Central"], "woe:alias_FRE_V": ["Aeroport Grand Central"], "woe:hierarchy": {"continent": 24865670, "country": 23424942, "town": 0, "planet": 1, "county": 56189422, "suburb": 0, "state": 2346981, "region": 0, "localadmin": 56189710}, "woe:timezone_id": 28350704, "woe:hash": "kekh0kcgxxy2", "woe:centroid": [28.13872, -25.98889], "geom:latitude": -25.98889, "geom:longitude": 28.13872, "geom:hash": "kekh0kcgxxy2", "woe:latitude": -25.98889, "geom:centroid": [28.13872, -25.98889], "woe:longitude": 28.13872, "woe:repo": "woeplanet-airport-za", "geom:area": 0.0, "woe:scale": 19}}