{"type": "Feature", "id": 12517421, "geometry": {"type": "Point", "coordinates": [29.6056, -26.016701]}, "properties": {"woe:id": 12517421, "woe:parent_id": 55881312, "woe:name": "Hendrina Power Station Airport", "woe:placetype": 14, "woe:placetype_name": "Airport", "woe:lang": "ENG", "iso:country": "ZA", "meta:provider": ["geoplanet:7.3.1", "geoplanet:7.3.2", "geoplanet:7.4.0", "geoplanet:7.4.1", "geoplanet:7.5.1", "geoplanet:7.5.2", "geoplanet:7.6.0", "geoplanet:7.8.1", "geoplanet:7.9.0", "geoplanet:7.10.0", "geoplanet:8.0.0", "woeplanet:8.0.0"], "meta:indexed": "2020-08-20T21:02:22.304885", "meta:updated": "2020-10-14T12:10:56.768977", "woe:hierarchy": {"continent": 24865670, "country": 23424942, "town": 0, "planet": 1, "county": 56189425, "suburb": 0, "state": 2346983, "region": 0, "localadmin": 56189586}, "woe:timezone_id": 28350704, "woe:hash": "kem5cxy1srrm", "woe:centroid": [29.6056, -26.016701], "geom:latitude": -26.016701, "geom:longitude": 29.6056, "geom:hash": "kem5cxy1srrm", "woe:latitude": -26.016701, "geom:centroid": [29.6056, -26.016701], "woe:longitude": 29.6056, "woe:repo": "woeplanet-airport-za", "geom:area": 0.0, "woe:scale": 19}}