{"type": "Feature", "id": 12517495, "geometry": {"type": "Point", "coordinates": [30.799999, -27.7889]}, "properties": {"woe:id": 12517495, "woe:parent_id": 1588711, "woe:name": "Vryheid Airport", "woe:placetype": 14, "woe:placetype_name": "Airport", "woe:lang": "ENG", "iso:country": "ZA", "meta:provider": ["geoplanet:7.3.1", "geoplanet:7.3.2", "geoplanet:7.4.0", "geoplanet:7.4.1", "geoplanet:7.5.1", "geoplanet:7.5.2", "geoplanet:7.6.0", "geoplanet:7.8.1", "geoplanet:7.9.0", "geoplanet:7.10.0", "geoplanet:8.0.0", "woeplanet:8.0.0"], "meta:indexed": "2020-08-20T21:02:22.356384", "woe:alias_ENG_V": ["VYD Airport", "VYD"], "meta:updated": "2020-10-14T12:10:56.799335", "woe:hierarchy": {"continent": 24865670, "country": 23424942, "town": 0, "planet": 1, "county": 56189413, "suburb": 0, "state": 2346982, "region": 0, "localadmin": 56189615}, "woe:timezone_id": 28350704, "woe:hash": "kejcuv5vgvxf", "woe:centroid": [30.799999, -27.7889], "geom:latitude": -27.7889, "geom:longitude": 30.799999, "geom:hash": "kejcuv5vgvxf", "woe:latitude": -27.7889, "geom:centroid": [30.799999, -27.7889], "woe:longitude": 30.799999, "woe:repo": "woeplanet-airport-za", "geom:area": 0.0, "woe:scale": 19}}